[{
    "position": 1,
    "type": "Motherboard",
    "producer": "Asus",
    "name": "P8P67 Deluxe",
    "parameters": "bb",
    "quantity": "1",
    "description": "aa",
    "img": "https://www.empowerlaptop.com/wp-content/uploads/w1711/desktop/32828827776-2678164-1.jpg",
    "specs": "https://pl.empowerlaptop.com/p/asus-p8p67-deluxe-motherboard-w1711/",
    "shopName": "X-KOM",
    "shopLink": "https://www.x-kom.pl/p/64902-asus-p8p67-deluxe-r30-p67-3xpci-e-ddr3.html"
  },
  {
    "position": 2,
    "type": "Processor",
    "producer": "Intel",
    "name": "i7-2600K",
    "parameters": "OC @ 4400 MHz",
    "quantity": "1",
    "description": "",
    "img": "",
    "specs": "https://ark.intel.com/content/www/pl/pl/ark/products/52214/intel-core-i7-2600k-processor-8m-cache-up-to-3-80-ghz.html",
    "shopName": "",
    "shopLink": ""
  },
  {
    "position": 3,
    "type": "Cooling",
    "producer": "Thermalright",
    "name": "Venomous X",
    "parameters": "",
    "quantity": "1",
    "description": "",
    "img": "",
    "specs": "https://pclab.pl/art44739-47.html",
    "shopName": "",
    "shopLink": ""
  },
  {
    "position": 4,
    "type": "Memory - Channel 1",
    "producer": "G Skill",
    "name": "ECO F3-12800CL8-4GB",
    "parameters": "4GB DDR3-1333",
    "quantity": "2",
    "description": "",
    "img": "",
    "specs": "https://www.gskill.com/specification/165/177/1532326662/F3-12800CL8D-4GBECO-Specification",
    "shopName": "",
    "shopLink": ""
  },
  {
    "position": 5,
    "type": "Memory - Channel 2",
    "producer": "G Skill",
    "name": "Ripjaws F3-12800CL8-2GBRM",
    "parameters": "2GB DDR3-1333",
    "quantity": "2",
    "description": "",
    "img": "",
    "specs": "https://www.gskill.com/product/165/183/1532515223/F3-12800CL8D-2GBTDTridentDDR3-1600MHz-CL8-8-8-1.60V2GB-(2x1GB)",
    "shopName": "",
    "shopLink": ""
  },
  {
    "position": 6,
    "type": "Hard drive",
    "producer": "Samsung",
    "name": "SSD 860 EVO 500GB",
    "parameters": "",
    "quantity": "1",
    "description": "",
    "img": "",
    "specs": "",
    "shopName": "",
    "shopLink": ""
  },
  {
    "position": 7,
    "type": "Hard drive",
    "producer": "Seagate",
    "name": "BarraCuda 2 TB ST2000DL003-9VT166",
    "parameters": "3.5\" 5400 RPM",
    "quantity": "1",
    "description": "",
    "img": "",
    "specs": "",
    "shopName": "",
    "shopLink": ""
  },
  {
    "position": 8,
    "type": "Hard drive",
    "producer": "Samsung",
    "name": "HD154UI 1.5 TB",
    "parameters": "3.5\" 5400 RPM",
    "quantity": "1",
    "description": "",
    "img": "",
    "specs": "",
    "shopName": "",
    "shopLink": ""
  },
  {
    "position": 9,
    "type": "Hard drive",
    "producer": "Seagate",
    "name": "BarraCuda 500 GB ST3500320AS",
    "parameters": "3.5\" 7200 RPM",
    "quantity": "1",
    "description": "",
    "img": "",
    "specs": "",
    "shopName": "",
    "shopLink": ""
  },
  {
    "position": 10,
    "type": "Graphics Card",
    "producer": "Nvidia",
    "name": "GeForce GTX 760",
    "parameters": "2 GB DDR5",
    "quantity": "1",
    "description": "",
    "img": "https://www.purepc.pl/files/Image/artykul_zdjecia/2013/GeForce_GTX_760_Compare/asus_gtx_760_directcu_ii_test_review_1.jpg",
    "specs": "https://www.nvidia.pl/gtx-700-graphics-cards/gtx-760/",
    "shopName": "",
    "shopLink": ""
  },
  {
    "position": 11,
    "type": "Case",
    "producer": "Fractal Design",
    "name": "Define R3",
    "parameters": "Titanium Grey",
    "quantity": "1",
    "description": "",
    "img": "",
    "specs": "https://www.fractal-design.com/",
    "shopName": "",
    "shopLink": ""
  },
  {
    "position": 12,
    "type": "Power Supply",
    "producer": "SeaSonic",
    "name": "M12II-620 EVO SS-620GM2 F2",
    "parameters": "620 W",
    "quantity": "1",
    "description": "",
    "img": "",
    "specs": "https://seasonic.com/m12ii-evo",
    "shopName": "",
    "shopLink": ""
  }
]
